[{"mtype":"INNINGS_RUNS","groupById":"29749615","provider":"FANCY","btype":"LINE","name":"Match 1st over run(QG vs KK)adv","id":"1.170098349-3.FY","runners":[{"lay":[{"line":"6","price":"100"}],"name":"Match 1st over run(QG vs KK)adv","back":[{"line":"7","price":"100"}],"id":"3"}],"oddsType":"HAAR_JEET","statusLabel":"","status":""},{"mtype":"INNINGS_RUNS","groupById":"29749615","provider":"FANCY","btype":"LINE","name":"6 over runs QG(QG vs KK)adv","id":"1.170098349-4.FY","runners":[{"lay":[{"line":"45","price":"100"}],"name":"6 over runs QG(QG vs KK)adv","back":[{"line":"47","price":"100"}],"id":"4"}],"oddsType":"HAAR_JEET","statusLabel":"","status":""},{"mtype":"INNINGS_RUNS","groupById":"29749615","provider":"FANCY","btype":"LINE","name":"6 over runs KK(QG vs KK)adv","id":"1.170098349-5.FY","runners":[{"lay":[{"line":"47","price":"100"}],"name":"6 over runs KK(QG vs KK)adv","back":[{"line":"49","price":"100"}],"id":"5"}],"oddsType":"HAAR_JEET","statusLabel":"","status":""},{"mtype":"INNINGS_RUNS","groupById":"29749615","provider":"FANCY","btype":"LINE","name":"20 over runs QG(QG vs KK)adv","id":"1.170098349-6.FY","runners":[{"lay":[{"line":"162","price":"100"}],"name":"20 over runs QG(QG vs KK)adv","back":[{"line":"164","price":"100"}],"id":"6"}],"oddsType":"HAAR_JEET","statusLabel":"","status":""},{"mtype":"INNINGS_RUNS","groupById":"29749615","provider":"FANCY","btype":"LINE","name":"20 over runs KK(QG vs KK)adv","id":"1.170098349-7.FY","runners":[{"lay":[{"line":"167","price":"100"}],"name":"20 over runs KK(QG vs KK)adv","back":[{"line":"169","price":"100"}],"id":"7"}],"oddsType":"HAAR_JEET","statusLabel":"","status":""},{"mtype":"INNINGS_RUNS","groupById":"29749615","provider":"FANCY","btype":"LINE","name":"Fall of 1st Wkt QG(QG vs KK)adv","id":"1.170098349-8.FY","runners":[{"lay":[{"line":"24","price":"110"}],"name":"Fall of 1st Wkt QG(QG vs KK)adv","back":[{"line":"24","price":"90"}],"id":"8"}],"oddsType":"HAAR_JEET","statusLabel":"","status":""},{"mtype":"INNINGS_RUNS","groupById":"29749615","provider":"FANCY","btype":"LINE","name":"Fall of 1st Wkt KK(QG vs KK)adv","id":"1.170098349-9.FY","runners":[{"lay":[{"line":"27","price":"110"}],"name":"Fall of 1st Wkt KK(QG vs KK)adv","back":[{"line":"27","price":"90"}],"id":"9"}],"oddsType":"HAAR_JEET","statusLabel":"","status":""},{"mtype":"INNINGS_RUNS","groupById":"29749615","provider":"FANCY","btype":"LINE","name":"A Shehzad run(QG vs KK)adv","id":"1.170098349-10.FY","runners":[{"lay":[{"line":"23","price":"110"}],"name":"A Shehzad run(QG vs KK)adv","back":[{"line":"23","price":"90"}],"id":"10"}],"oddsType":"HAAR_JEET","statusLabel":"","status":""},{"mtype":"INNINGS_RUNS","groupById":"29749615","provider":"FANCY","btype":"LINE","name":"Ahsan Ali run(QG vs KK)adv","id":"1.170098349-11.FY","runners":[{"lay":[{"line":"21","price":"110"}],"name":"Ahsan Ali run(QG vs KK)adv","back":[{"line":"21","price":"90"}],"id":"11"}],"oddsType":"HAAR_JEET","statusLabel":"","status":""},{"mtype":"INNINGS_RUNS","groupById":"29749615","provider":"FANCY","btype":"LINE","name":"S Khan run(QG vs KK)adv","id":"1.170098349-12.FY","runners":[{"lay":[{"line":"22","price":"110"}],"name":"S Khan run(QG vs KK)adv","back":[{"line":"22","price":"90"}],"id":"12"}],"oddsType":"HAAR_JEET","statusLabel":"","status":""},{"mtype":"INNINGS_RUNS","groupById":"29749615","provider":"FANCY","btype":"LINE","name":"B Azam run(QG vs KK)adv","id":"1.170098349-13.FY","runners":[{"lay":[{"line":"32","price":"110"}],"name":"B Azam run(QG vs KK)adv","back":[{"line":"32","price":"90"}],"id":"13"}],"oddsType":"HAAR_JEET","statusLabel":"","status":""},{"mtype":"INNINGS_RUNS","groupById":"29749615","provider":"FANCY","btype":"LINE","name":"K Manzoor run(QG vs KK)adv","id":"1.170098349-42.FY","runners":[{"lay":[{"line":"20","price":"110"}],"name":"K Manzoor run(QG vs KK)adv","back":[{"line":"20","price":"90"}],"id":"42"}],"oddsType":"HAAR_JEET","statusLabel":"","status":""},{"mtype":"INNINGS_RUNS","groupById":"29749615","provider":"FANCY","btype":"LINE","name":"A Shehzad Boundaries(QG vs KK)adv","id":"1.170098349-14.FY","runners":[{"lay":[{"line":"3","price":"100"}],"name":"A Shehzad Boundaries(QG vs KK)adv","back":[{"line":"4","price":"100"}],"id":"14"}],"oddsType":"HAAR_JEET","statusLabel":"","status":""},{"mtype":"INNINGS_RUNS","groupById":"29749615","provider":"FANCY","btype":"LINE","name":"Ahsan Ali Boundaries(QG vs KK)adv","id":"1.170098349-15.FY","runners":[{"lay":[{"line":"3","price":"100"}],"name":"Ahsan Ali Boundaries(QG vs KK)adv","back":[{"line":"4","price":"100"}],"id":"15"}],"oddsType":"HAAR_JEET","statusLabel":"","status":""},{"mtype":"INNINGS_RUNS","groupById":"29749615","provider":"FANCY","btype":"LINE","name":"S Khan Boundaries(QG vs KK)adv","id":"1.170098349-16.FY","runners":[{"lay":[{"line":"3","price":"100"}],"name":"S Khan Boundaries(QG vs KK)adv","back":[{"line":"4","price":"100"}],"id":"16"}],"oddsType":"HAAR_JEET","statusLabel":"","status":""},{"mtype":"INNINGS_RUNS","groupById":"29749615","provider":"FANCY","btype":"LINE","name":"B Azam Boundaries(QG vs KK)adv","id":"1.170098349-17.FY","runners":[{"lay":[{"line":"4","price":"100"}],"name":"B Azam Boundaries(QG vs KK)adv","back":[{"line":"5","price":"100"}],"id":"17"}],"oddsType":"HAAR_JEET","statusLabel":"","status":""},{"mtype":"INNINGS_RUNS","groupById":"29749615","provider":"FANCY","btype":"LINE","name":"K Manzoor Boundaries(QG vs KK)adv","id":"1.170098349-43.FY","runners":[{"lay":[{"line":"3","price":"115"}],"name":"K Manzoor Boundaries(QG vs KK)adv","back":[{"line":"3","price":"85"}],"id":"43"}],"oddsType":"HAAR_JEET","statusLabel":"","status":""},{"mtype":"INNINGS_RUNS","groupById":"29749615","provider":"FANCY","btype":"LINE","name":"1st Wkt lost to QG balls(QG vs KK)adv","id":"1.170098349-18.FY","runners":[{"lay":[{"line":"17","price":"100"}],"name":"1st Wkt lost to QG balls(QG vs KK)adv","back":[{"line":"19","price":"100"}],"id":"18"}],"oddsType":"HAAR_JEET","statusLabel":"","status":""},{"mtype":"INNINGS_RUNS","groupById":"29749615","provider":"FANCY","btype":"LINE","name":"1st Wkt lost to KK balls(QG vs KK)adv","id":"1.170098349-19.FY","runners":[{"lay":[{"line":"20","price":"100"}],"name":"1st Wkt lost to KK balls(QG vs KK)adv","back":[{"line":"22","price":"100"}],"id":"19"}],"oddsType":"HAAR_JEET","statusLabel":"","status":""},{"mtype":"INNINGS_RUNS","groupById":"29749615","provider":"FANCY","btype":"LINE","name":"How many balls for 50 runs QG(QG vs KK)adv","id":"1.170098349-20.FY","runners":[{"lay":[{"line":"39","price":"100"}],"name":"How many balls for 50 runs QG(QG vs KK)adv","back":[{"line":"41","price":"100"}],"id":"20"}],"oddsType":"HAAR_JEET","statusLabel":"","status":""},{"mtype":"INNINGS_RUNS","groupById":"29749615","provider":"FANCY","btype":"LINE","name":"How many balls for 50 runs KK(QG vs KK)adv","id":"1.170098349-21.FY","runners":[{"lay":[{"line":"37","price":"100"}],"name":"How many balls for 50 runs KK(QG vs KK)adv","back":[{"line":"39","price":"100"}],"id":"21"}],"oddsType":"HAAR_JEET","statusLabel":"","status":""},{"mtype":"INNINGS_RUNS","groupById":"29749615","provider":"FANCY","btype":"LINE","name":"Total match Fours(QG vs KK)adv","id":"1.170098349-22.FY","runners":[{"lay":[{"line":"25","price":"100"}],"name":"Total match Fours(QG vs KK)adv","back":[{"line":"27","price":"100"}],"id":"22"}],"oddsType":"HAAR_JEET","statusLabel":"","status":""},{"mtype":"INNINGS_RUNS","groupById":"29749615","provider":"FANCY","btype":"LINE","name":"Total match Sixes(QG vs KK)adv","id":"1.170098349-23.FY","runners":[{"lay":[{"line":"10","price":"100"}],"name":"Total match Sixes(QG vs KK)adv","back":[{"line":"12","price":"100"}],"id":"23"}],"oddsType":"HAAR_JEET","statusLabel":"","status":""},{"mtype":"INNINGS_RUNS","groupById":"29749615","provider":"FANCY","btype":"LINE","name":"Total match Boundaries(QG vs KK)adv","id":"1.170098349-24.FY","runners":[{"lay":[{"line":"35","price":"100"}],"name":"Total match Boundaries(QG vs KK)adv","back":[{"line":"37","price":"100"}],"id":"24"}],"oddsType":"HAAR_JEET","statusLabel":"","status":""},{"mtype":"INNINGS_RUNS","groupById":"29749615","provider":"FANCY","btype":"LINE","name":"Total match Wkts(QG vs KK)adv","id":"1.170098349-25.FY","runners":[{"lay":[{"line":"12","price":"100"}],"name":"Total match Wkts(QG vs KK)adv","back":[{"line":"13","price":"100"}],"id":"25"}],"oddsType":"HAAR_JEET","statusLabel":"","status":""},{"mtype":"INNINGS_RUNS","groupById":"29749615","provider":"FANCY","btype":"LINE","name":"Total match Wides(QG vs KK)adv","id":"1.170098349-26.FY","runners":[{"lay":[{"line":"8","price":"100"}],"name":"Total match Wides(QG vs KK)adv","back":[{"line":"9","price":"100"}],"id":"26"}],"oddsType":"HAAR_JEET","statusLabel":"","status":""},{"mtype":"INNINGS_RUNS","groupById":"29749615","provider":"FANCY","btype":"LINE","name":"Total match Extras(QG vs KK)adv","id":"1.170098349-27.FY","runners":[{"lay":[{"line":"14","price":"100"}],"name":"Total match Extras(QG vs KK)adv","back":[{"line":"16","price":"100"}],"id":"27"}],"oddsType":"HAAR_JEET","statusLabel":"","status":""},{"mtype":"INNINGS_RUNS","groupById":"29749615","provider":"FANCY","btype":"LINE","name":"Total match Caught Outs(QG vs KK)adv","id":"1.170098349-28.FY","runners":[{"lay":[{"line":"9","price":"100"}],"name":"Total match Caught Outs(QG vs KK)adv","back":[{"line":"10","price":"100"}],"id":"28"}],"oddsType":"HAAR_JEET","statusLabel":"","status":""},{"mtype":"INNINGS_RUNS","groupById":"29749615","provider":"FANCY","btype":"LINE","name":"Total match Bowled(QG vs KK)adv","id":"1.170098349-29.FY","runners":[{"lay":[{"line":"2","price":"100"}],"name":"Total match Bowled(QG vs KK)adv","back":[{"line":"3","price":"100"}],"id":"29"}],"oddsType":"HAAR_JEET","statusLabel":"","status":""},{"mtype":"INNINGS_RUNS","groupById":"29749615","provider":"FANCY","btype":"LINE","name":"Total match LBW(QG vs KK)adv","id":"1.170098349-30.FY","runners":[{"lay":[{"line":"1","price":"100"}],"name":"Total match LBW(QG vs KK)adv","back":[{"line":"2","price":"100"}],"id":"30"}],"oddsType":"HAAR_JEET","statusLabel":"","status":""},{"mtype":"INNINGS_RUNS","groupById":"29749615","provider":"FANCY","btype":"LINE","name":"Total match No-balls(QG vs KK)adv","id":"1.170098349-32.FY","runners":[{"lay":[{"line":"1","price":"100"}],"name":"Total match No-balls(QG vs KK)adv","back":[{"line":"2","price":"100"}],"id":"32"}],"oddsType":"HAAR_JEET","statusLabel":"","status":""},{"mtype":"INNINGS_RUNS","groupById":"29749615","provider":"FANCY","btype":"LINE","name":"Total match Fifties(QG vs KK)adv","id":"1.170098349-33.FY","runners":[{"lay":[{"line":"2","price":"100"}],"name":"Total match Fifties(QG vs KK)adv","back":[{"line":"3","price":"100"}],"id":"33"}],"oddsType":"HAAR_JEET","statusLabel":"","status":""},{"mtype":"INNINGS_RUNS","groupById":"29749615","provider":"FANCY","btype":"LINE","name":"Highest Scoring over in match(QG vs KK)adv","id":"1.170098349-34.FY","runners":[{"lay":[{"line":"19","price":"100"}],"name":"Highest Scoring over in match(QG vs KK)adv","back":[{"line":"20","price":"100"}],"id":"34"}],"oddsType":"HAAR_JEET","statusLabel":"","status":""},{"mtype":"INNINGS_RUNS","groupById":"29749615","provider":"FANCY","btype":"LINE","name":"Top batsman runs in match(QG vs KK)adv","id":"1.170098349-35.FY","runners":[{"lay":[{"line":"65","price":"100"}],"name":"Top batsman runs in match(QG vs KK)adv","back":[{"line":"67","price":"100"}],"id":"35"}],"oddsType":"HAAR_JEET","statusLabel":"","status":""},{"mtype":"INNINGS_RUNS","groupById":"29749615","provider":"FANCY","btype":"LINE","name":"3 Wkt or more by bowler in match(QG vs KK)adv","id":"1.170098349-36.FY","runners":[{"lay":[{"line":"3","price":"100"}],"name":"3 Wkt or more by bowler in match(QG vs KK)adv","back":[{"line":"4","price":"100"}],"id":"36"}],"oddsType":"HAAR_JEET","statusLabel":"","status":""},{"mtype":"INNINGS_RUNS","groupById":"29749615","provider":"FANCY","btype":"LINE","name":"Multiplication of Total Fours QG and KK adv","id":"1.170098349-37.FY","runners":[{"lay":[{"line":"167","price":"100"}],"name":"Multiplication of Total Fours QG and KK adv","back":[{"line":"172","price":"100"}],"id":"37"}],"oddsType":"HAAR_JEET","statusLabel":"","status":""},{"mtype":"INNINGS_RUNS","groupById":"29749615","provider":"FANCY","btype":"LINE","name":"Multiplication of Total Sixes QG and KK adv","id":"1.170098349-38.FY","runners":[{"lay":[{"line":"28","price":"100"}],"name":"Multiplication of Total Sixes QG and KK adv","back":[{"line":"33","price":"100"}],"id":"38"}],"oddsType":"HAAR_JEET","statusLabel":"","status":""},{"mtype":"INNINGS_RUNS","groupById":"29749615","provider":"FANCY","btype":"LINE","name":"Multiplication of Total Wkts QG and KK adv","id":"1.170098349-39.FY","runners":[{"lay":[{"line":"32","price":"100"}],"name":"Multiplication of Total Wkts QG and KK adv","back":[{"line":"37","price":"100"}],"id":"39"}],"oddsType":"HAAR_JEET","statusLabel":"","status":""},{"mtype":"INNINGS_RUNS","groupById":"29749615","provider":"FANCY","btype":"LINE","name":"Multiplication of Total Wides QG and KK adv","id":"1.170098349-40.FY","runners":[{"lay":[{"line":"12","price":"100"}],"name":"Multiplication of Total Wides QG and KK adv","back":[{"line":"17","price":"100"}],"id":"40"}],"oddsType":"HAAR_JEET","statusLabel":"","status":""},{"mtype":"INNINGS_RUNS","groupById":"29749615","provider":"FANCY","btype":"LINE","name":"Multiplication of Total Extras QG and KK adv","id":"1.170098349-41.FY","runners":[{"lay":[{"line":"48","price":"100"}],"name":"Multiplication of Total Extras QG and KK adv","back":[{"line":"52","price":"100"}],"id":"41"}],"oddsType":"HAAR_JEET","statusLabel":"","status":""}]